EulerKit/__init__.py
EulerKit/figuratenumbers.py
EulerKit/listtools.py
EulerKit/palindromes.py
EulerKit/pandigital.py
EulerKit/primes.py
EulerKit/timer.py
EulerKit/wait.py
eulerkit-0.4.0.dist-info/METADATA
eulerkit-0.4.0.dist-info/WHEEL
eulerkit-0.4.0.dist-info/licenses/LICENSE
eulerkit-0.4.0.dist-info/RECORD
