Metadata-Version: 2.4
Name: EulerKit
Version: 0.4.0
Summary: A package with some utilities inspired by Project Euler Problems
Project-URL: Homepage, https://github.com/MarcoPlatino/EulerKit
Project-URL: Issues, https://github.com/MarcoPlatino/EulerKit/issues
Project-URL: Wiki, https://github.com/MarcoPlatino/EulerKit/wiki
Author-email: Marco Platino <mnplatino@gmail.com>
License-Expression: MIT
License-File: LICENSE
Classifier: Operating System :: OS Independent
Classifier: Programming Language :: Python :: 3
Requires-Python: >=3.9
